odoo/addons/uom_category_active/README.rst
odoo/addons/uom_category_active/__init__.py
odoo/addons/uom_category_active/__manifest__.py
odoo/addons/uom_category_active/i18n/it.po
odoo/addons/uom_category_active/i18n/uom_category_active.pot
odoo/addons/uom_category_active/models/__init__.py
odoo/addons/uom_category_active/models/uom_category.py
odoo/addons/uom_category_active/readme/CONTRIBUTORS.md
odoo/addons/uom_category_active/readme/DESCRIPTION.md
odoo/addons/uom_category_active/readme/USAGE.md
odoo/addons/uom_category_active/static/description/icon.png
odoo/addons/uom_category_active/static/description/index.html
odoo/addons/uom_category_active/tests/__init__.py
odoo/addons/uom_category_active/tests/test_uom_category_active.py
odoo/addons/uom_category_active/views/uom_category_views.xml
odoo_addon_uom_category_active-17.0.1.0.1.dist-info/METADATA
odoo_addon_uom_category_active-17.0.1.0.1.dist-info/WHEEL
odoo_addon_uom_category_active-17.0.1.0.1.dist-info/top_level.txt
odoo_addon_uom_category_active-17.0.1.0.1.dist-info/RECORD
