Metadata-Version: 2.1
Name: odoo-addon-uom_category_active
Version: 17.0.1.0.1
Requires-Python: >=3.10
Requires-Dist: odoo>=17.0a,<17.1dev
Summary: Add option to archive UoM categories
Home-page: https://github.com/OCA/product-attribute
License: AGPL-3
Author: PESOL, Odoo Community Association (OCA)
Author-email: support@odoo-community.org
Classifier: Programming Language :: Python
Classifier: Framework :: Odoo
Classifier: Framework :: Odoo :: 17.0
Classifier: License :: OSI Approved :: GNU Affero General Public License v3
